{
  "name": "escalation-routing",
  "version": "1.0.0",
  "description": "Decide whether a feedback item is in-scope for the Supervisor or must be escalated to AlexMaster (framework-level)",
  "author": {
    "name": "ACT Plugin Mall"
  },
  "keywords": [
    "escalation",
    "routing",
    "decide",
    "whether",
    "feedback",
    "item",
    "in-scope",
    "supervisor"
  ],
  "engines": [
    "copilot"
  ],
  "shape": ".S..",
  "category": "supervisor-fleet",
  "tier": "standard",
  "token_cost": 1794,
  "requires_edition": ">=1.0.0",
  "requires_plugins": [],
  "artifacts": {
    "skill": "SKILL.md"
  },
  "install_paths": {
    "skill": ".github/skills/local/escalation-routing/SKILL.md"
  }
}
